flask_mongoengine2/__init__.py
flask_mongoengine2/_version.py
flask_mongoengine2/connection.py
flask_mongoengine2/decorators.py
flask_mongoengine2/documents.py
flask_mongoengine2/pagination.py
flask_mongoengine2/panels.py
flask_mongoengine2/sessions.py
flask_mongoengine2/templates/panels/mongo-panel.html
flask_mongoengine2-2.2.0.dist-info/AUTHORS.md
flask_mongoengine2-2.2.0.dist-info/LICENSE.md
flask_mongoengine2-2.2.0.dist-info/METADATA
flask_mongoengine2-2.2.0.dist-info/WHEEL
flask_mongoengine2-2.2.0.dist-info/top_level.txt
flask_mongoengine2-2.2.0.dist-info/RECORD
